xylib.py
_xylib.cpython-36m-x86_64-linux-gnu.so
xylib_py_wheels-1.7.3.dist-info/top_level.txt
xylib_py_wheels-1.7.3.dist-info/WHEEL
xylib_py_wheels-1.7.3.dist-info/COPYING
xylib_py_wheels-1.7.3.dist-info/RECORD
xylib_py_wheels-1.7.3.dist-info/METADATA
