Metadata-Version: 2.1
Name: xylib-py-wheels
Version: 1.7.3
Summary: Built wheels for xylib by Marcin Wojdyr
Home-page: https://github.com/wojdyr/xylib
Author: Christopher Stallard
Author-email: christopher.stallard1@gmail.com
License: LGPL2.1
Platform: UNKNOWN
Classifier: Development Status :: 5 - Production/Stable
Classifier: Intended Audience :: Developers
Classifier: Intended Audience :: Science/Research
Classifier: Programming Language :: Python :: Implementation :: CPython
Classifier: Topic :: Scientific/Engineering :: Chemistry
Classifier: Topic :: Software Development :: Libraries :: Python Modules
License-File: COPYING
